Metadata-Version: 1.1
Name: pysourcebin
Version: 0.0.4
Summary: a sourcebin api wrapper
Home-page: UNKNOWN
Author: Amashi
Author-email: amashisenpai386@gmail.com
License: MIT
Keywords: sourcebin,source,bin
Platform: UNKNOWN
Classifier: Development Status :: 5 - Production/Stable
Classifier: Intended Audience :: Education
Classifier: Operating System :: Microsoft :: Windows :: Windows 10
Classifier: License :: OSI Approved :: MIT License
Classifier: Programming Language :: Python :: 3
